qtdraw/__init__.py
qtdraw/core/dialog_about.py
qtdraw/core/dialog_preference.py
qtdraw/core/pyvista_widget.py
qtdraw/core/pyvista_widget_setting.py
qtdraw/core/qtdraw.png
qtdraw/core/qtdraw_app.py
qtdraw/multipie/dialog_info.py
qtdraw/multipie/dialog_modulation.py
qtdraw/multipie/dialog_multipie.py
qtdraw/multipie/plugin_multipie.py
qtdraw/multipie/plugin_multipie_setting.py
qtdraw/multipie/util.py
qtdraw/parser/converter.py
qtdraw/parser/data_group.py
qtdraw/parser/element.py
qtdraw/parser/read_material.py
qtdraw/parser/util.py
qtdraw/parser/vesta.py
qtdraw/parser/xsf.py
qtdraw/scripts/conv_qtdraw2.py
qtdraw/scripts/qtdraw.py
qtdraw/util/basic_object.py
qtdraw/util/color_selector_util.py
qtdraw/util/latex_to_png.py
qtdraw/util/latex_to_svg.py
qtdraw/util/logging_util.py
qtdraw/util/pdf_viewer.py
qtdraw/util/qt_event_util.py
qtdraw/util/util.py
qtdraw/util/util_axis.py
qtdraw/util/util_str.py
qtdraw/widget/custom_widget.py
qtdraw/widget/delegate.py
qtdraw/widget/group_model.py
qtdraw/widget/group_view.py
qtdraw/widget/message_box.py
qtdraw/widget/tab_group_view.py
qtdraw/widget/table_view.py
qtdraw/widget/validator.py
qtdraw-2.4.2.dist-info/licenses/LICENSE
qtdraw-2.4.2.dist-info/METADATA
qtdraw-2.4.2.dist-info/WHEEL
qtdraw-2.4.2.dist-info/entry_points.txt
qtdraw-2.4.2.dist-info/top_level.txt
qtdraw-2.4.2.dist-info/RECORD
