Metadata-Version: 2.4
Name: qtdraw
Version: 2.4.2
Summary: 3D drawing tool for molecules and crystals based on Pyvista and PySide6.
Author-email: Hiroaki Kusunose <hiroaki.kusunose@gmail.com>
License: MIT
Project-URL: Homepage, https://github.com/CMT-MU/QtDraw
Project-URL: Issues, https://github.com/CMT-MU/QtDraw/issues
Keywords: pyvista,PySide6,multipie
Classifier: Intended Audience :: Science/Research
Classifier: Topic :: Scientific/Engineering :: Information Analysis
Classifier: License :: OSI Approved :: MIT License
Classifier: Operating System :: Microsoft :: Windows
Classifier: Operating System :: POSIX
Classifier: Operating System :: MacOS
Classifier: Programming Language :: Python :: 3.11
Classifier: Programming Language :: Python :: 3.12
Classifier: Programming Language :: Python :: 3.13
Requires-Python: >=3.11
License-File: LICENSE
Requires-Dist: numpy
Requires-Dist: Cython
Requires-Dist: matplotlib
Requires-Dist: PySide6
Requires-Dist: pyvista
Requires-Dist: pyvistaqt
Requires-Dist: click
Requires-Dist: black
Requires-Dist: ipython
Requires-Dist: pymatgen
Requires-Dist: gcoreutils
Requires-Dist: multipie
Provides-Extra: dev
Requires-Dist: jupyter-book; extra == "dev"
Requires-Dist: ghp-import; extra == "dev"
Dynamic: license-file
